pygifconvt_p_fe/__init__.py
pygifconvt_p_fe/converter.py
pygifconvt_p_fe-1.0.0.dist-info/LICENSE
pygifconvt_p_fe-1.0.0.dist-info/METADATA
pygifconvt_p_fe-1.0.0.dist-info/WHEEL
pygifconvt_p_fe-1.0.0.dist-info/top_level.txt
pygifconvt_p_fe-1.0.0.dist-info/RECORD
